{
  "project_info": {
    "project_number": "414429242328",
    "project_id": "gigaturnip-b6b5b",
    "storage_bucket": "gigaturnip-b6b5b.appspot.com"
  },
  "client": [
    {
      "client_info": {
        "mobilesdk_app_id": "1:414429242328:android:2916c95425e866b467c8ad",
        "android_client_info": {
          "package_name": "kg.kloop.android.gigaturnip"
        }
      },
      "oauth_client": [
        {
          "client_id": "414429242328-g868e8bsqhrglsds2qd7tseopkvg6o01.apps.googleusercontent.com",
          "client_type": 1,
          "android_info": {
            "package_name": "kg.kloop.android.gigaturnip",
            "certificate_hash": "f08417a341d3e322bcff1ebb0befa31b53cecf2b"
          }
        },
        {
          "client_id": "414429242328-iv4aqlufmg92t8unh4n5av0498egl296.apps.googleusercontent.com",
          "client_type": 1,
          "android_info": {
            "package_name": "kg.kloop.android.gigaturnip",
            "certificate_hash": "2730ff1f848968f186b3cff66726715d388f3b37"
          }
        },
        {
          "client_id": "414429242328-hocr7f7afl2j39mq46s5h877fm6s2e41.apps.googleusercontent.com",
          "client_type": 3
        }
      ],
      "api_key": [
        {
          "current_key": "AIzaSyBvPwWECwMSkjp4-MCOYFInHWGpYWk1Cuo"
        }
      ],
      "services": {
        "appinvite_service": {
          "other_platform_oauth_client": [
            {
              "client_id": "414429242328-hocr7f7afl2j39mq46s5h877fm6s2e41.apps.googleusercontent.com",
              "client_type": 3
            }
          ]
        }
      }
    }
  ],
  "configuration_version": "1"
}